llamaindex_agentserver/__init__.py
llamaindex_agentserver/adapter.py
llamaindex_agentserver/models/__init__.py
llamaindex_agentserver/models/request_converter.py
llamaindex_agentserver/models/response_converter.py
llamaindex_agentserver/models/state_converter.py
llamaindex_agentserver/models/stream_response_converter.py
llamaindex_agentserver/models/response_event_generators/__init__.py
llamaindex_agentserver/models/response_event_generators/base.py
llamaindex_agentserver/models/response_event_generators/output_item_generator.py
llamaindex_agentserver/models/response_event_generators/stream_generator.py
llamaindex_agentserver_adapter-0.1.0.dist-info/METADATA
llamaindex_agentserver_adapter-0.1.0.dist-info/WHEEL
llamaindex_agentserver_adapter-0.1.0.dist-info/licenses/LICENSE
llamaindex_agentserver_adapter-0.1.0.dist-info/RECORD
