Metadata-Version: 2.4
Name: llamaindex-agentserver-adapter
Version: 0.1.0
Summary: LlamaIndex Workflows adapter for Azure AI Agent Server
Project-URL: Homepage, https://github.com/yourusername/llamaindex-agentserver-adapter
Project-URL: Documentation, https://github.com/yourusername/llamaindex-agentserver-adapter#readme
Project-URL: Repository, https://github.com/yourusername/llamaindex-agentserver-adapter
Project-URL: Issues, https://github.com/yourusername/llamaindex-agentserver-adapter/issues
Author-email: Your Name <your.email@example.com>
License: MIT
License-File: LICENSE
Keywords: agents,ai,azure,llama-index,llamaindex,workflows
Classifier: Development Status :: 4 - Beta
Classifier: Intended Audience :: Developers
Classifier: License :: OSI Approved :: MIT License
Classifier: Operating System :: OS Independent
Classifier: Programming Language :: Python :: 3
Classifier: Programming Language :: Python :: 3.10
Classifier: Programming Language :: Python :: 3.11
Classifier: Programming Language :: Python :: 3.12
Classifier: Programming Language :: Python :: 3.13
Classifier: Topic :: Scientific/Engineering :: Artificial Intelligence
Requires-Python: >=3.10
Requires-Dist: azure-ai-agentserver-core>=1.0.0b1
Requires-Dist: llama-index-core>=0.12.0
Requires-Dist: llama-index-workflows>=0.1.0
Provides-Extra: all
Requires-Dist: llama-index-llms-azure-openai>=0.3.0; extra == 'all'
Requires-Dist: llama-index-llms-openai>=0.3.0; extra == 'all'
Requires-Dist: mypy>=1.0.0; extra == 'all'
Requires-Dist: pytest-asyncio>=0.21.0; extra == 'all'
Requires-Dist: pytest>=7.0.0; extra == 'all'
Requires-Dist: ruff>=0.1.0; extra == 'all'
Provides-Extra: azure-openai
Requires-Dist: llama-index-llms-azure-openai>=0.3.0; extra == 'azure-openai'
Provides-Extra: dev
Requires-Dist: mypy>=1.0.0; extra == 'dev'
Requires-Dist: pytest-asyncio>=0.21.0; extra == 'dev'
Requires-Dist: pytest>=7.0.0; extra == 'dev'
Requires-Dist: ruff>=0.1.0; extra == 'dev'
Provides-Extra: openai
Requires-Dist: llama-index-llms-openai>=0.3.0; extra == 'openai'
